{ "frames": [
   {
    "filename": "WindowSpriteSheet.aseprite",
    "frame": { "x": 0, "y": 0, "w": 512, "h": 384 },
    "rotated": false,
    "trimmed": false,
    "spriteSourceSize": { "x": 0, "y": 0, "w": 512, "h": 384 },
    "sourceSize": { "w": 512, "h": 384 },
    "duration": 100
   }
 ],
 "meta": {
  "app": "https://www.aseprite.org/",
  "version": "1.2.30-x64",
  "image": "WindowSpriteSheet.png",
  "format": "RGBA8888",
  "size": { "w": 512, "h": 384 },
  "scale": "1",
  "frameTags": [
  ],
  "layers": [
   { "name": "Checkbox", "opacity": 255, "blendMode": "normal" },
   { "name": "ControlButtons", "opacity": 255, "blendMode": "normal" }
  ],
  "slices": [
   { "name": "ButtonLeft", "color": "#0000ffff", "data": "Idle,Left", "keys": [{ "frame": 0, "bounds": {"x": 10, "y": 0, "w": 6, "h": 64 } }] },
   { "name": "ButtonMiddle", "color": "#0000ffff", "data": "Idle,Center", "keys": [{ "frame": 0, "bounds": {"x": 16, "y": 0, "w": 16, "h": 64 } }] },
   { "name": "ButtonRight", "color": "#0000ffff", "data": "Idle,Right", "keys": [{ "frame": 0, "bounds": {"x": 32, "y": 0, "w": 6, "h": 64 } }] },
   { "name": "ButtonLeft_Active", "color": "#0000ffff", "data": "Active,Left", "keys": [{ "frame": 0, "bounds": {"x": 10, "y": 64, "w": 6, "h": 64 } }] },
   { "name": "ButtonRight_Active", "color": "#0000ffff", "data": "Active,Right", "keys": [{ "frame": 0, "bounds": {"x": 32, "y": 64, "w": 6, "h": 64 } }] },
   { "name": "ButtonMiddle_Active", "color": "#0000ffff", "data": "Active,Center", "keys": [{ "frame": 0, "bounds": {"x": 16, "y": 64, "w": 16, "h": 64 } }] },
   { "name": "Checkbox", "color": "#0000ffff", "data": "Idle", "keys": [{ "frame": 0, "bounds": {"x": 65, "y": 0, "w": 32, "h": 32 } }] },
   { "name": "Checkbox_Active", "color": "#0000ffff", "data": "Active", "keys": [{ "frame": 0, "bounds": {"x": 96, "y": 0, "w": 32, "h": 32 } }] },
   { "name": "Checkbox_Active_Checked", "color": "#0000ffff", "data": "Active,Checked", "keys": [{ "frame": 0, "bounds": {"x": 96, "y": 32, "w": 32, "h": 32 } }] },
   { "name": "Checkbox_Checked", "color": "#0000ffff", "data": "Idle,Checked", "keys": [{ "frame": 0, "bounds": {"x": 64, "y": 32, "w": 32, "h": 32 } }] }
  ]
 }
}
